py_lsh/__init__.py
py_lsh/lshash.py
py_lsh/storage.py
py_lsh-0.0.2.dist-info/LICENSE
py_lsh-0.0.2.dist-info/METADATA
py_lsh-0.0.2.dist-info/WHEEL
py_lsh-0.0.2.dist-info/top_level.txt
py_lsh-0.0.2.dist-info/RECORD
