Metadata-Version: 2.1
Name: py-lsh
Version: 0.0.2
Summary: A Python implementation of locality sensitive hashing.
Home-page: https://github.com/guofei9987/py_lsh
Author: Guo Fei
Author-email: guofei9987@foxmail.com
License: MIT
Platform: linux
Platform: windows
Platform: macos
Requires-Python: >=3.5
Requires-Dist: numpy
